mat3ra/__init__.py
mat3ra/regex/__init__.py
mat3ra/regex/data/__init__.py
mat3ra/regex/data/schemas.py
mat3ra_regex-2024.4.19.post1.dist-info/LICENSE.md
mat3ra_regex-2024.4.19.post1.dist-info/METADATA
mat3ra_regex-2024.4.19.post1.dist-info/WHEEL
mat3ra_regex-2024.4.19.post1.dist-info/top_level.txt
mat3ra_regex-2024.4.19.post1.dist-info/RECORD
