Metadata-Version: 2.1
Name: mat3ra-regex
Version: 2024.4.19.post1
Summary: Mat3ra Regex.
Author-email: "Exabyte Inc." <info@mat3ra.com>
License: # LICENSE
Classifier: Programming Language :: Python
Classifier: Programming Language :: Python :: 3
Classifier: Development Status :: 3 - Alpha
Classifier: Topic :: Software Development
Requires-Python: >=3.8
License-File: LICENSE.md
Requires-Dist: numpy
Provides-Extra: all
Requires-Dist: mat3ra-regex[dev] ; extra == 'all'
Requires-Dist: mat3ra-regex[tests] ; extra == 'all'
Provides-Extra: dev
Requires-Dist: pre-commit ; extra == 'dev'
Requires-Dist: black ; extra == 'dev'
Requires-Dist: ruff ; extra == 'dev'
Requires-Dist: isort ; extra == 'dev'
Requires-Dist: mypy ; extra == 'dev'
Requires-Dist: pip-tools ; extra == 'dev'
Provides-Extra: tests
Requires-Dist: coverage ; extra == 'tests'
Requires-Dist: mock ; extra == 'tests'
Requires-Dist: pytest ; extra == 'tests'
Requires-Dist: pytest-cov ; extra == 'tests'
Requires-Dist: mat3ra-fixtures ; extra == 'tests'
